selfish/__init__.py
selfish-0.3.1.dist-info/LICENSE.txt
selfish-0.3.1.dist-info/METADATA
selfish-0.3.1.dist-info/WHEEL
selfish-0.3.1.dist-info/top_level.txt
selfish-0.3.1.dist-info/RECORD
