Metadata-Version: 2.1
Name: selfish
Version: 0.3.1
Summary: implicit self
Author: Daniel Pepper
License: The MIT License (MIT)
Project-URL: Homepage, https://github.com/dpep/selfish_py
Keywords: simplify
Classifier: License :: OSI Approved :: MIT License
Classifier: Topic :: Utilities
Requires-Python: >=3
License-File: LICENSE.txt
Requires-Dist: ambiguous
Provides-Extra: test
Requires-Dist: isort >=5.13 ; extra == 'test'
Requires-Dist: pytest >=8.2 ; extra == 'test'
